{
  "annotations": {
    "changelogDate": "20250923212846"
  },
  "dto": "mapstruct",
  "fields": [
    {
      "fieldName": "quantity",
      "fieldType": "Integer",
      "fieldValidateRules": []
    },
    {
      "fieldName": "unitPrice",
      "fieldType": "BigDecimal"
    },
    {
      "fieldName": "totalPrice",
      "fieldType": "BigDecimal"
    }
  ],
  "jpaMetamodelFiltering": false,
  "name": "OrderItem",
  "pagination": "pagination",
  "readOnly": false,
  "relationships": [
    {
      "otherEntityField": "id",
      "otherEntityName": "order",
      "otherEntityRelationshipName": "orderItem",
      "relationshipName": "order",
      "relationshipSide": "left",
      "relationshipType": "many-to-one"
    },
    {
      "otherEntityField": "id",
      "otherEntityName": "book",
      "relationshipName": "book",
      "relationshipSide": "left",
      "relationshipType": "many-to-one"
    }
  ],
  "searchEngine": "no",
  "service": "serviceClass"
}
